trojanrat_scripts/__init__.py
trojanrat_scripts/all_ai_scripts.txt
trojanrat_scripts/cli.py
trojanrat_ai_scripts-0.2.0.dist-info/METADATA
trojanrat_ai_scripts-0.2.0.dist-info/WHEEL
trojanrat_ai_scripts-0.2.0.dist-info/entry_points.txt
trojanrat_ai_scripts-0.2.0.dist-info/top_level.txt
trojanrat_ai_scripts-0.2.0.dist-info/RECORD
