Metadata-Version: 2.4
Name: trojanrat-ai-scripts
Version: 0.2.0
Summary: A tool to place a collection of AI scripts into your current project folder.
Author: trojanrat
Dynamic: author
Dynamic: summary
